README.txt
setup.cfg
setup.py
Products/__init__.py
Products.AttachmentTypes.egg-info/PKG-INFO
Products.AttachmentTypes.egg-info/SOURCES.txt
Products.AttachmentTypes.egg-info/dependency_links.txt
Products.AttachmentTypes.egg-info/entry_points.txt
Products.AttachmentTypes.egg-info/namespace_packages.txt
Products.AttachmentTypes.egg-info/not-zip-safe
Products.AttachmentTypes.egg-info/requires.txt
Products.AttachmentTypes.egg-info/top_level.txt
Products/AttachmentTypes/__init__.py
Products/AttachmentTypes/config.py
Products/AttachmentTypes/configure.zcml
Products/AttachmentTypes/setuphandlers.py
Products/AttachmentTypes/utils.py
Products/AttachmentTypes/content/__init__.py
Products/AttachmentTypes/content/file.py
Products/AttachmentTypes/content/image.py
Products/AttachmentTypes/content/link.py
Products/AttachmentTypes/i18n/AttachmentTypes-de-plone.po
Products/AttachmentTypes/i18n/AttachmentTypes-fr-plone.po
Products/AttachmentTypes/kss/__init__.py
Products/AttachmentTypes/kss/configure.zcml
Products/AttachmentTypes/kss/dynamicattachments.kss
Products/AttachmentTypes/kss/views.py
Products/AttachmentTypes/profiles/default/attachmenttypes_various.txt
Products/AttachmentTypes/profiles/default/factorytool.xml
Products/AttachmentTypes/profiles/default/import_steps.xml
Products/AttachmentTypes/profiles/default/kssregistry.xml
Products/AttachmentTypes/profiles/default/metadata.xml
Products/AttachmentTypes/profiles/default/propertiestool.xml
Products/AttachmentTypes/profiles/default/rolemap.xml
Products/AttachmentTypes/profiles/default/skins.xml
Products/AttachmentTypes/profiles/default/types.xml
Products/AttachmentTypes/profiles/default/workflows.xml
Products/AttachmentTypes/profiles/default/types/FileAttachment.xml
Products/AttachmentTypes/profiles/default/types/ImageAttachment.xml
Products/AttachmentTypes/profiles/default/types/LinkAttachment.xml
Products/AttachmentTypes/skins/attachment_widget/doAddAttachments.py
Products/AttachmentTypes/skins/attachment_widget/doAddImages.py
Products/AttachmentTypes/skins/attachment_widget/doAddLinks.py
Products/AttachmentTypes/skins/attachment_widget/doDeleteAttachments.py
Products/AttachmentTypes/skins/attachment_widget/doEditLinks.py
Products/AttachmentTypes/skins/attachment_widget/doMoveDownAttachments.py
Products/AttachmentTypes/skins/attachment_widget/doMoveUpAttachments.py
