Metadata-Version: 1.0
Name: Products.AttachmentTypes
Version: 1.6
Summary: Provides attachment content types for link, image, and file
Home-page: http://raptus.com
Author: Raptus AG
Author-email: skaeser@raptus.com
License: GPL
Keywords: plone archetypes attachment content
Platform: UNKNOWN
Classifier: Programming Language :: Python
Classifier: Topic :: Software Development :: Libraries :: Python Modules
